GitHacker/__init__.py
GitHacker-1.1.7.dist-info/METADATA
GitHacker-1.1.7.dist-info/WHEEL
GitHacker-1.1.7.dist-info/entry_points.txt
GitHacker-1.1.7.dist-info/top_level.txt
GitHacker-1.1.7.dist-info/RECORD
