Metadata-Version: 2.1
Name: GitHacker
Version: 1.1.7
Summary: A multiple threads tool to download the `.git` folder and rebuild git repository locally.
Home-page: https://github.com/WangYihang/GitHacker
Author: Yihang Wang
Author-email: wangyihanger@gmail.com
License: UNKNOWN
Keywords: ctf,git,web,security
Platform: UNKNOWN
Classifier: Programming Language :: Python :: 3
Classifier: Development Status :: 5 - Production/Stable
Classifier: Topic :: Security
Classifier: Topic :: Software Development :: Version Control :: Git
Classifier: Topic :: Software Development :: Version Control
Classifier: License :: OSI Approved :: GNU Lesser General Public License v3 (LGPLv3)
Requires-Python: >=3.6
Requires-Dist: GitPython
Requires-Dist: beautifulsoup4
Requires-Dist: coloredlogs
Requires-Dist: requests
Requires-Dist: semver
